open_data_project/.gitignore
open_data_project/LICENSE
open_data_project/ODPCategories.json
open_data_project/__init__.py
open_data_project/arcgis.py
open_data_project/ckan.py
open_data_project/dcat.py
open_data_project/error_log.md
open_data_project/export2jkan.py
open_data_project/log.json
open_data_project/log.md
open_data_project/main.sh
open_data_project/merge_data.py
open_data_project/odp.py
open_data_project/processor.py
open_data_project/requirements.txt
open_data_project/sources.csv
open_data_project/sparkql_statistics.py
open_data_project/usmart.py
open_data_project/.github/LICENSE
open_data_project/.github/workflows/alive.yml
open_data_project/.github/workflows/pipeline.yml
open_data_project/.github/workflows/test.yml
open_data_project/health_checks/health_categories.py
open_data_project/tests/__init__.py
open_data_project/tests/arcgis_test.py
open_data_project/tests/ckan_test.py
open_data_project/tests/conftest.py
open_data_project/tests/dcat_test.py
open_data_project/tests/export2jkan_test.py
open_data_project/tests/generate_new_mock_data.py
open_data_project/tests/how_to_test.md
open_data_project/tests/merge_data_test.py
open_data_project/tests/processor_test.py
open_data_project/tests/usmart_test.py
open_data_project/tests/mock_data/get_json_data.json
open_data_project/tests/mock_data/mockcsv.csv
open_data_project/tests/mock_data/arcgis/renfrew.json
open_data_project/tests/mock_data/arcgis/expected/renfrew.csv
open_data_project/tests/mock_data/dcat/glasgow.json
open_data_project/tests/mock_data/dcat/expected/glasgow.csv
open_data_project/tests/mock_data/output/mockcsv.csv
open_data_project/tests/mock_data/output/arcgis/renfrew.csv
open_data_project/tests/mock_data/output/dcat/glasgow.csv
open_data_project/tests/mock_data/output/usmart/Dumfries and Galloway Council.csv
open_data_project/tests/mock_data/usmart/Dumfries and Galloway Council.json
open_data_project/tests/mock_data/usmart/expected/Dumfries and Galloway Council.csv
open_data_project-0.2.dist-info/LICENSE
open_data_project-0.2.dist-info/METADATA
open_data_project-0.2.dist-info/WHEEL
open_data_project-0.2.dist-info/entry_points.txt
open_data_project-0.2.dist-info/top_level.txt
open_data_project-0.2.dist-info/RECORD
