Metadata-Version: 2.1
Name: open-data-project
Version: 0.2
Summary: A Python package to retrieve the data for your open data portal and to launch the front-end structure for its website.
Author: Danail Dimov
Author-email: d.dimov62@gmail.com
License-File: LICENSE
Requires-Dist: beautifulsoup4
Requires-Dist: black
Requires-Dist: datefinder
Requires-Dist: Markdown
Requires-Dist: pandas (==1.4.4)
Requires-Dist: pytest (==7.1.2)
Requires-Dist: PyYAML (==6.0)
Requires-Dist: PyGithub
Requires-Dist: requests
Requires-Dist: flake8
Requires-Dist: validators
Requires-Dist: python-dateutil
